{"CV143": {"PersonalStatement": [{"text": "Theresa Parker, born on 1973-04-25, is a Female based in East Christopher, Zimbabwe. She is Divorced and holds Algerian nationality. Currently working at Shaffer Inc."}], "WorkExperience": [{"text": "HR Manager at Fowler PLC from 2012 to 2020."}, {"text": "Senior Data Analyst at Shaffer Inc, 2022 to present."}], "EducationAndTraining": [{"text": "Master's in Business Administration from Washington University in St. Louis"}, {"text": "Master's in Engineering from Al Ain University"}], "PersonalSkills": [{"text": "Adaptability: Able to quickly learn and implement new technologies."}, {"text": "Leadership: Proven track record of managing cross-functional teams."}], "Hobbies": [{"text": "In their free time, she enjoys cycling."}]}}